COPYING.MIT
INSTALL.rst
MANIFEST.in
README.rst
setup.py
milk/__init__.py
milk/milk_version.py
milk/nfoldcrossvalidation.py
milk.egg-info/PKG-INFO
milk.egg-info/SOURCES.txt
milk.egg-info/dependency_links.txt
milk.egg-info/top_level.txt
milk/active/__init__.py
milk/active/eimpact.py
milk/active/uncertainty.py
milk/demos/__init__.py
milk/demos/adaboost.py
milk/demos/rf_wine_2d.py
milk/demos/svm-decision-boundary.py
milk/ext/__init__.py
milk/ext/jugparallel.py
milk/measures/__init__.py
milk/measures/cluster_agreement.py
milk/measures/curves.py
milk/measures/measures.py
milk/measures/nfoldcrossvalidation.py
milk/supervised/__init__.py
milk/supervised/_lasso.cpp
milk/supervised/_perceptron.cpp
milk/supervised/_svm.cpp
milk/supervised/_tree.cpp
milk/supervised/adaboost.py
milk/supervised/base.py
milk/supervised/classifier.py
milk/supervised/defaultclassifier.py
milk/supervised/defaultlearner.py
milk/supervised/featureselection.py
milk/supervised/gridsearch.py
milk/supervised/grouped.py
milk/supervised/knn.py
milk/supervised/lasso.py
milk/supervised/logistic.py
milk/supervised/multi.py
milk/supervised/multi_label.py
milk/supervised/multi_view.py
milk/supervised/normalise.py
milk/supervised/parzen.py
milk/supervised/perceptron.py
milk/supervised/precluster.py
milk/supervised/precluster_learner.py
milk/supervised/randomforest.py
milk/supervised/set2binary_array.py
milk/supervised/svm.py
milk/supervised/tree.py
milk/supervised/weighted_voting_adaboost.py
milk/supervised/eigen3/Eigen/Array
milk/supervised/eigen3/Eigen/CMakeLists.txt
milk/supervised/eigen3/Eigen/Cholesky
milk/supervised/eigen3/Eigen/CholmodSupport
milk/supervised/eigen3/Eigen/Core
milk/supervised/eigen3/Eigen/Dense
milk/supervised/eigen3/Eigen/Eigen
milk/supervised/eigen3/Eigen/Eigen2Support
milk/supervised/eigen3/Eigen/Eigenvalues
milk/supervised/eigen3/Eigen/Geometry
milk/supervised/eigen3/Eigen/Householder
milk/supervised/eigen3/Eigen/IterativeLinearSolvers
milk/supervised/eigen3/Eigen/Jacobi
milk/supervised/eigen3/Eigen/LU
milk/supervised/eigen3/Eigen/LeastSquares
milk/supervised/eigen3/Eigen/OrderingMethods
