Metadata-Version: 1.0
Name: milk
Version: 0.6.1
Summary: Machine Learning Toolkit
Home-page: http://luispedro.org/software/milk
Author: Luis Pedro Coelho
Author-email: luis@luispedro.org
License: MIT
Platform: UNKNOWN
